rucio/__init__.py
rucio/alembicrevision.py
rucio/vcsversion.py
rucio/version.py
rucio/web/__init__.py
rucio/web/ui/__init__.py
rucio/web/ui/main.py
rucio/web/ui/flask/__init__.py
rucio/web/ui/flask/bp.py
rucio/web/ui/flask/main.py
rucio/web/ui/flask/common/__init__.py
rucio/web/ui/flask/common/utils.py
rucio/web/ui/flask/common/saml/advanced_settings.json
rucio/web/ui/flask/common/saml/settings.json
rucio/web/ui/flask/common/saml/certs/README
rucio/web/ui/flask/templates/account.html
rucio/web/ui/flask/templates/account_rse_usage.html
rucio/web/ui/flask/templates/account_usage.html
rucio/web/ui/flask/templates/account_usage_history.html
rucio/web/ui/flask/templates/accounting.html
rucio/web/ui/flask/templates/accounts.html
rucio/web/ui/flask/templates/add_rse.html
rucio/web/ui/flask/templates/approve_rules.html
rucio/web/ui/flask/templates/atlas_index.html
rucio/web/ui/flask/templates/backlog_mon.html
rucio/web/ui/flask/templates/bad_replicas.html
rucio/web/ui/flask/templates/bad_replicas_summary.html
rucio/web/ui/flask/templates/base.html
rucio/web/ui/flask/templates/cond.html
rucio/web/ui/flask/templates/dbrelease.html
rucio/web/ui/flask/templates/did.html
rucio/web/ui/flask/templates/dumps.html
rucio/web/ui/flask/templates/heartbeats.html
rucio/web/ui/flask/templates/index.html
rucio/web/ui/flask/templates/infrastructure.html
rucio/web/ui/flask/templates/lifetime_exception.html
rucio/web/ui/flask/templates/list_lifetime_exceptions.html
rucio/web/ui/flask/templates/list_rules.html
rucio/web/ui/flask/templates/login.html
rucio/web/ui/flask/templates/no_certificate.html
rucio/web/ui/flask/templates/problem.html
rucio/web/ui/flask/templates/request_rule.html
rucio/web/ui/flask/templates/rse.html
rucio/web/ui/flask/templates/rse_account_usage.html
rucio/web/ui/flask/templates/rse_add_protocol.html
rucio/web/ui/flask/templates/rse_locks.html
rucio/web/ui/flask/templates/rse_usage.html
rucio/web/ui/flask/templates/rses.html
rucio/web/ui/flask/templates/rule.html
rucio_webui-39.1.0.dist-info/licenses/LICENSE
rucio_webui-39.1.0.dist-info/METADATA
rucio_webui-39.1.0.dist-info/WHEEL
rucio_webui-39.1.0.dist-info/top_level.txt
rucio_webui-39.1.0.dist-info/RECORD
