Metadata-Version: 2.4
Name: rucio-webui
Version: 39.1.0
Summary: Rucio WebUI package
Author-email: Rucio <rucio-contact@cern.ch>
Maintainer-email: Rucio <rucio-contact@cern.ch>
License-Expression: Apache-2.0
Project-URL: Homepage, https://rucio.cern.ch/
Project-URL: Documentation, https://rucio.cern.ch/documentation/
Project-URL: Repository, https://github.com/rucio/rucio.git
Project-URL: Bug Tracker, https://github.com/rucio/rucio/issues
Project-URL: Changelog, https://rucio.cern.ch/documentation/release-notes/
Classifier: Development Status :: 5 - Production/Stable
Classifier: Intended Audience :: Information Technology
Classifier: Intended Audience :: System Administrators
Classifier: Operating System :: POSIX :: Linux
Classifier: Natural Language :: English
Classifier: Programming Language :: Python
Classifier: Programming Language :: Python :: 3
Classifier: Programming Language :: Python :: 3.9
Classifier: Programming Language :: Python :: 3.10
Classifier: Environment :: No Input/Output (Daemon)
Requires-Python: >=3.9
License-File: LICENSE
Requires-Dist: rucio>=1.2.5
Dynamic: license-file
